eoglib/__init__.py
eoglib/biomarkers.py
eoglib/calibration.py
eoglib/consts.py
eoglib/differentiation.py
eoglib/errors.py
eoglib/filtering.py
eoglib/stimulation.py
eoglib/identification/__init__.py
eoglib/identification/saccades.py
eoglib/io/__init__.py
eoglib/io/diff.py
eoglib/io/eog.py
eoglib/io/openbci.py
eoglib/io/openeog.py
eoglib/io/otoscreen.py
eoglib/io/protocols.py
eoglib/models/__init__.py
eoglib/models/annotations.py
eoglib/models/base.py
eoglib/models/channels.py
eoglib/models/hardware.py
eoglib/models/protocols.py
eoglib/models/stimulus.py
eoglib/models/study.py
eoglib/models/subjects.py
eoglib/models/tests.py
eoglib-0.2.1.dist-info/METADATA
eoglib-0.2.1.dist-info/WHEEL
eoglib-0.2.1.dist-info/entry_points.txt
eoglib-0.2.1.dist-info/license_files/LICENSE
eoglib-0.2.1.dist-info/RECORD
